<annotation>
	<folder>train-images</folder>
	<filename>label-3.jpg</filename>
	<path>D:\projects\Comp680Project\training\images\train-images\label-3.jpg</path>
	<source>
		<database>Unknown</database>
	</source>
	<size>
		<width>2592</width>
		<height>1944</height>
		<depth>3</depth>
	</size>
	<segmented>0</segmented>
	<object>
		<name>label</name>
		<pose>Unspecified</pose>
		<truncated>0</truncated>
		<difficult>0</difficult>
		<bndbox>
			<xmin>1184</xmin>
			<ymin>566</ymin>
			<xmax>1821</xmax>
			<ymax>1674</ymax>
		</bndbox>
	</object>
</annotation>
